fin4py/__init__.py
fin4py/finance.py
fin4py-0.0.2.dist-info/LICENSE.txt
fin4py-0.0.2.dist-info/METADATA
fin4py-0.0.2.dist-info/WHEEL
fin4py-0.0.2.dist-info/top_level.txt
fin4py-0.0.2.dist-info/RECORD
