Metadata-Version: 2.1
Name: fin4py
Version: 0.0.2
Summary: financial-calculator
Home-page: https://github.com/ahadnur/pyFinance
Author: Md. Ahadujjaman Nur
Author-email: ahadnur44@gmail.com
License: UNKNOWN
Platform: UNKNOWN
Classifier: Programming Language :: Python :: 3
Classifier: License :: OSI Approved :: MIT License
Classifier: Operating System :: OS Independent
